{
  "content": [
    {
      "content": null,
      "created": "2024-09-19T10:29:51.134612Z",
      "format": null,
      "hash": null,
      "hash_algorithm": null,
      "last_modified": "2024-09-19T10:29:48.936596Z",
      "mimetype": "image/png",
      "name": "ptolemaic.png",
      "path": "images/ptolemaic.png",
      "size": 44705,
      "type": "file",
      "writable": true
    },
    {
      "content": null,
      "created": "2024-09-19T10:29:51.133612Z",
      "format": null,
      "hash": null,
      "hash_algorithm": null,
      "last_modified": "2024-09-19T10:29:48.936596Z",
      "mimetype": "image/png",
      "name": "mosquito_banner.png",
      "path": "images/mosquito_banner.png",
      "size": 105515,
      "type": "file",
      "writable": true
    },
    {
      "content": null,
      "created": "2024-09-19T10:29:51.132612Z",
      "format": null,
      "hash": null,
      "hash_algorithm": null,
      "last_modified": "2024-09-19T10:29:48.936596Z",
      "mimetype": "image/jpeg",
      "name": "ind_t_test.jpg",
      "path": "images/ind_t_test.jpg",
      "size": 378679,
      "type": "file",
      "writable": true
    },
    {
      "content": null,
      "created": "2024-09-19T10:29:51.134612Z",
      "format": null,
      "hash": null,
      "hash_algorithm": null,
      "last_modified": "2024-09-19T10:29:48.936596Z",
      "mimetype": "image/jpeg",
      "name": "munch_scream.jpg",
      "path": "images/munch_scream.jpg",
      "size": 137265,
      "type": "file",
      "writable": true
    }
  ],
  "created": "2024-09-19T10:29:51.134612Z",
  "format": "json",
  "hash": null,
  "hash_algorithm": null,
  "last_modified": "2024-09-19T10:29:51.134612Z",
  "mimetype": null,
  "name": "images",
  "path": "images",
  "size": null,
  "type": "directory",
  "writable": true
}